conject/__init__.py
conject/_container.py
conject/_container_config.py
conject/_ctx_mgr.py
conject/_dep_spec.py
conject/_expressions.py
conject/_impl.py
conject/_types.py
conject/_utils.py
conject/_validation.py
conject/py.typed
conject/utils.py
conject-0.4.0.dist-info/WHEEL
conject-0.4.0.dist-info/METADATA
conject-0.4.0.dist-info/RECORD
