Metadata-Version: 2.1
Name: conject
Version: 0.4.0
Summary: Dependency Injection and configuration library.
Home-page: https://github.com/xppt/py-conject
Author: xppt
Author-email: 21246102+xppt@users.noreply.github.com
Requires-Python: >=3.6,<4.0
Classifier: Programming Language :: Python :: 3
Classifier: Programming Language :: Python :: 3.6
Classifier: Programming Language :: Python :: 3.7
Classifier: Programming Language :: Python :: 3.8
Classifier: Programming Language :: Python :: 3.9
Requires-Dist: async-exit-stack
Requires-Dist: async-generator
Requires-Dist: pydantic
